LICENSE
README.md
sqlite3_cache/__init__.py
sqlite3_cache/cache.py
sqlite3_cache-0.2.2.dist-info/LICENSE
sqlite3_cache-0.2.2.dist-info/METADATA
sqlite3_cache-0.2.2.dist-info/WHEEL
sqlite3_cache-0.2.2.dist-info/RECORD
