Metadata-Version: 2.1
Name: sqlite3-cache
Version: 0.2.2
Summary: Use SQLite3 as cache.
Home-page: https://github.com/MrThearMan/sqlite3-cache
License: MIT
Keywords: sqlite,sqlite3,cache
Author: Matti Lamppu
Author-email: lamppu.matti.akseli@gmail.com
Requires-Python: >=3.8,<4
Classifier: Environment :: Web Environment
Classifier: Intended Audience :: Developers
Classifier: License :: OSI Approved :: MIT License
Classifier: Natural Language :: English
Classifier: Programming Language :: Python
Classifier: Programming Language :: Python :: 3
Classifier: Programming Language :: Python :: 3.8
Classifier: Programming Language :: Python :: 3.9
Classifier: Programming Language :: Python :: 3.10
Classifier: Programming Language :: Python :: 3.11
Classifier: Programming Language :: Python :: 3.12
Classifier: Programming Language :: Python :: 3 :: Only
Project-URL: Bug Tracker, https://github.com/MrThearMan/sqlite3-cache/issues
Project-URL: Repository, https://github.com/MrThearMan/sqlite3-cache
